vibegate/__init__.py
vibegate/__main__.py
vibegate/artifacts.py
vibegate/checks.py
vibegate/cli.py
vibegate/config.py
vibegate/evidence.py
vibegate/findings.py
vibegate/policy_semantic.py
vibegate/proposals.py
vibegate/py.typed
vibegate/runner.py
vibegate/schema_loader.py
vibegate/tuning.py
vibegate/workspace.py
vibegate/llm/__init__.py
vibegate/llm/cache.py
vibegate/llm/enhancer.py
vibegate/llm/ollama.py
vibegate/llm/openai_compatible.py
vibegate/llm/prompts.py
vibegate/llm/providers.py
vibegate/llm/recommend.py
vibegate/llm/setup.py
vibegate/plugins/__init__.py
vibegate/plugins/api.py
vibegate/plugins/loader.py
vibegate/plugins/types.py
vibegate/schemas/__init__.py
vibegate/schemas/fixpack.schema.json
vibegate/schemas/vibegate-events.schema.json
vibegate/schemas/vibegate.schema.json
vibegate/ui/__init__.py
vibegate/ui/server.py
vibegate/ui/static/style.css
vibegate/ux/__init__.py
vibegate/ux/summary.py
vibegate-0.6.2.dist-info/METADATA
vibegate-0.6.2.dist-info/WHEEL
vibegate-0.6.2.dist-info/entry_points.txt
vibegate-0.6.2.dist-info/licenses/LICENSE
vibegate-0.6.2.dist-info/RECORD
