Metadata-Version: 2.3
Name: vibegate
Version: 0.6.2
Summary: Deterministic production readiness gate for Python projects.
Project-URL: source, https://github.com/VibeGate/vibegate
Project-URL: issues, https://github.com/VibeGate/vibegate/issues
Project-URL: docs, https://github.com/VibeGate/vibegate/tree/main/docs
Author: VibeGate
License: MIT
License-File: LICENSE
Keywords: cli,django,fastapi,flask,gate,linting,python,quality,testing
Classifier: Development Status :: 3 - Alpha
Classifier: Intended Audience :: Developers
Classifier: License :: OSI Approved :: MIT License
Classifier: Programming Language :: Python :: 3
Classifier: Programming Language :: Python :: 3 :: Only
Classifier: Programming Language :: Python :: 3.10
Classifier: Programming Language :: Python :: 3.11
Classifier: Programming Language :: Python :: 3.12
Requires-Python: >=3.10
Requires-Dist: click<9,>=8.1
Requires-Dist: jsonschema<5,>=4.23
Requires-Dist: pyyaml<7,>=6.0
Requires-Dist: tomli<3,>=2.0; python_version < '3.11'
Requires-Dist: typer<1,>=0.12
Provides-Extra: dev
Requires-Dist: build==1.2.2.post1; extra == 'dev'
Requires-Dist: commitizen==4.1.0; extra == 'dev'
Requires-Dist: distlib==0.3.9; extra == 'dev'
Requires-Dist: pre-commit==4.0.1; extra == 'dev'
Requires-Dist: pyright==1.1.407; extra == 'dev'
Requires-Dist: pytest-cov==7.0.0; extra == 'dev'
Requires-Dist: pytest==8.3.2; extra == 'dev'
Requires-Dist: python-semantic-release==9.15.2; extra == 'dev'
Requires-Dist: ruff==0.14.9; extra == 'dev'
Requires-Dist: twine==5.1.1; extra == 'dev'
Requires-Dist: uv==0.5.7; extra == 'dev'
Provides-Extra: llm
Requires-Dist: ollama<1,>=0.4.0; extra == 'llm'
Provides-Extra: tools
Requires-Dist: pyright==1.1.407; extra == 'tools'
Requires-Dist: pytest==8.3.2; extra == 'tools'
Requires-Dist: ruff==0.14.9; extra == 'tools'
Requires-Dist: uv==0.5.7; extra == 'tools'
Provides-Extra: ui
Requires-Dist: fastapi<1,>=0.115; extra == 'ui'
Requires-Dist: httpx<1,>=0.27; extra == 'ui'
Requires-Dist: typing-extensions<5,>=4.1; extra == 'ui'
Requires-Dist: uvicorn<1,>=0.30; extra == 'ui'
